{"is_source_file": false, "format": "CSS", "description": "Stylesheet for the tic-tac-toe frontend application, defining the body and code styles.", "external_files": [], "external_methods": [], "published": [], "classes": [], "methods": [], "calls": [], "search-terms": ["stylesheet", "CSS styles", "tic-tac-toe frontend"], "state": 2, "file_id": 1, "knowledge_revision": 15, "git_revision": "6bafc9879d06e6d1b18f151373af8ad7487d019a", "hash": "6c2104b8d219ed99234ae2d6329f4357", "format-version": 4, "code-base-name": "tic_tac_toe_frontend", "filename": "tic_tac_toe_frontend/src/index.css", "revision_history": [{"15": "6bafc9879d06e6d1b18f151373af8ad7487d019a"}]}